tff_utils/__init__.py
tff_utils/configuration.py
tff_utils/connection.py
tff_utils/k8s.py
tff_utils-0.0.7.dist-info/METADATA
tff_utils-0.0.7.dist-info/WHEEL
tff_utils-0.0.7.dist-info/top_level.txt
tff_utils-0.0.7.dist-info/RECORD
